updatetable/__init__.py
updatetable/updatetable.py
updatetable-0.0.1.dist-info/DESCRIPTION.rst
updatetable-0.0.1.dist-info/METADATA
updatetable-0.0.1.dist-info/RECORD
updatetable-0.0.1.dist-info/WHEEL
updatetable-0.0.1.dist-info/metadata.json
updatetable-0.0.1.dist-info/top_level.txt
